{
  "schemaVersion": "v5",
  "themeId": "T_038",
  "themeName": "글로벌 로봇 액추에이터",
  "meta": {
    "periodDefault": "3d",
    "periodOptions": [
      "3d",
      "7d",
      "1m",
      "ytd",
      "1y",
      "3y"
    ],
    "dataAsOf": "2026-02-21T16:00:00+09:00",
    "notes": "g38 누적 import 기반 T_038 freeze",
    "sources": []
  },
  "nodes": [
    {
      "id": "T_038",
      "type": "THEME",
      "name": "글로벌 로봇 액추에이터"
    },
    {
      "id": "A_312",
      "type": "ASSET",
      "name": "록웰오토메이션",
      "exposure": {
        "ticker": "ROK",
        "exchange": "NYSE",
        "country": "US"
      },
      "metrics": {
        "return_3d": -4.094595485615072,
        "return_7d": -2.717645747408315,
        "return_1m": 4.962355374882743,
        "return_ytd": 9.486889976163603,
        "return_1y": 41.739751835249784,
        "return_3y": 61.322045177270866,
        "close": 436.36,
        "marketCap": 48555522640,
        "valuationAsOf": "2026-05-18",
        "valuationSource": "FMP",
        "returnsAsOf": "2026-05-18",
        "returnsSource": "FMP",
        "pe_ttm": null
      }
    },
    {
      "id": "A_209",
      "type": "ASSET",
      "name": "무그",
      "exposure": {
        "ticker": "MOG.A",
        "exchange": "NYSE",
        "country": "US"
      },
      "metrics": {
        "return_3d": -0.972128222482016,
        "return_7d": 1.3156238197154613,
        "return_1m": 2.2229279136233737,
        "return_ytd": 13.34507042253521,
        "return_1y": 73.8684238954305,
        "return_3y": null,
        "returnsAsOf": "2026-05-18",
        "returnsSource": "FMP",
        "close": null,
        "marketCap": null,
        "pe_ttm": null,
        "valuationAsOf": null,
        "valuationSource": null
      }
    },
    {
      "id": "A_313",
      "type": "ASSET",
      "name": "커티스-라이트",
      "exposure": {
        "ticker": "CW",
        "exchange": "NYSE",
        "country": "US"
      },
      "metrics": {
        "return_3d": -5.41411451398135,
        "return_7d": -1.9449774305315803,
        "return_1m": -3.440494800516547,
        "return_ytd": 24.102868723575256,
        "return_1y": 74.48355481319547,
        "return_3y": 334.21969558041445,
        "close": 710.34,
        "marketCap": 26240786436,
        "valuationAsOf": "2026-05-18",
        "valuationSource": "FMP",
        "returnsAsOf": "2026-05-18",
        "returnsSource": "FMP",
        "pe_ttm": null
      }
    },
    {
      "id": "A_091",
      "type": "ASSET",
      "name": "레인보우로보틱스",
      "exposure": {
        "ticker": "277810",
        "exchange": "KOSDAQ",
        "country": "KR"
      },
      "metrics": {
        "close": 666000,
        "marketCap": 16683877880000,
        "pe_ttm": null,
        "valuationAsOf": "2026-05-19",
        "valuationSource": "EODHD",
        "return_3d": -20.80856123662307,
        "return_7d": -15.051020408163263,
        "return_1m": 8.116883116883123,
        "return_ytd": 34.95440729483283,
        "return_1y": 137.01067615658366,
        "return_3y": 456.8561872909699,
        "returnsAsOf": "2026-05-19",
        "returnsSource": "EODHD"
      }
    },
    {
      "id": "A_092",
      "type": "ASSET",
      "name": "에스피지",
      "exposure": {
        "ticker": "058610",
        "exchange": "KOSDAQ",
        "country": "KR"
      },
      "metrics": {
        "close": 109800,
        "marketCap": 3206846256000,
        "pe_ttm": null,
        "valuationAsOf": "2026-05-19",
        "valuationSource": "EODHD",
        "return_3d": -15.990818668706963,
        "return_7d": -18.8470066518847,
        "return_1m": -3.68421052631579,
        "return_ytd": 32.76904474002418,
        "return_1y": 325.4114945720903,
        "return_3y": 226.3001485884101,
        "returnsAsOf": "2026-05-19",
        "returnsSource": "EODHD"
      }
    },
    {
      "id": "A_082",
      "type": "ASSET",
      "name": "로보티즈",
      "exposure": {
        "ticker": "108490",
        "exchange": "KOSDAQ",
        "country": "KR"
      },
      "metrics": {
        "close": 274000,
        "marketCap": 4227312028000,
        "pe_ttm": null,
        "valuationAsOf": "2026-05-19",
        "valuationSource": "EODHD",
        "return_3d": -19.648093841642233,
        "return_7d": -18.086696562032888,
        "return_1m": 0.9208103130755152,
        "return_ytd": 1.6697588126159513,
        "return_1y": 643.5549525101763,
        "return_3y": 655.341144038594,
        "returnsAsOf": "2026-05-19",
        "returnsSource": "EODHD"
      }
    },
    {
      "id": "A_318",
      "type": "ASSET",
      "name": "에스비비테크",
      "exposure": {
        "ticker": "389500",
        "exchange": "KOSDAQ",
        "country": "KR"
      },
      "metrics": {
        "close": 76200,
        "marketCap": 392068657600,
        "pe_ttm": null,
        "valuationAsOf": "2026-05-19",
        "valuationSource": "EODHD",
        "return_3d": -19.108280254777064,
        "return_7d": 6.424581005586583,
        "return_1m": 16.692189892802457,
        "return_ytd": 107.62942779291551,
        "return_1y": 248.74141876430204,
        "return_3y": 19.2488262910798,
        "returnsAsOf": "2026-05-19",
        "returnsSource": "EODHD"
      }
    },
    {
      "id": "A_319",
      "type": "ASSET",
      "name": "하이젠알앤엠",
      "exposure": {
        "ticker": "160190",
        "exchange": "KOSDAQ",
        "country": "KR"
      },
      "metrics": {
        "close": 35300,
        "marketCap": 2131272000000,
        "pe_ttm": null,
        "valuationAsOf": "2026-05-19",
        "valuationSource": "EODHD",
        "return_3d": -12.189054726368154,
        "return_7d": -14.837153196622433,
        "return_1m": -14.216281895504256,
        "return_ytd": -40.67226890756302,
        "return_1y": 4.903417533432397,
        "return_3y": null,
        "returnsAsOf": "2026-05-19",
        "returnsSource": "EODHD"
      }
    },
    {
      "id": "A_314",
      "type": "ASSET",
      "name": "나브테스코",
      "exposure": {
        "ticker": "6268",
        "exchange": "TSE",
        "country": "JP"
      },
      "metrics": {
        "return_3d": -7.111730869792576,
        "return_7d": 1.4467923091566748,
        "return_1m": 14.3071643071643,
        "return_ytd": 39.13838120104438,
        "return_1y": 143.22227293473298,
        "return_3y": null,
        "returnsAsOf": "2026-05-18",
        "returnsSource": "FMP",
        "close": 5329.0,
        "marketCap": 624476323067,
        "pe_ttm": null,
        "valuationAsOf": "2026-05-18",
        "valuationSource": "FMP"
      }
    },
    {
      "id": "A_315",
      "type": "ASSET",
      "name": "에스엠씨",
      "exposure": {
        "ticker": "6273",
        "exchange": "TSE",
        "country": "JP"
      },
      "metrics": {
        "return_3d": -20.735905044510382,
        "return_7d": -15.296803652968038,
        "return_1m": -6.965728615213152,
        "return_ytd": 16.179540709812112,
        "return_1y": 41.603053435114504,
        "return_3y": null,
        "returnsAsOf": "2026-05-18",
        "returnsSource": "FMP",
        "close": 66780.0,
        "marketCap": 4216429098000,
        "pe_ttm": null,
        "valuationAsOf": "2026-05-18",
        "valuationSource": "FMP"
      }
    },
    {
      "id": "A_316",
      "type": "ASSET",
      "name": "MISUMI그룹",
      "exposure": {
        "ticker": "9962",
        "exchange": "TSE",
        "country": "JP"
      },
      "metrics": {
        "return_3d": -4.1958041958041985,
        "return_7d": -8.719582850521434,
        "return_1m": 5.578823923605292,
        "return_ytd": 25.78842315369261,
        "return_1y": 61.0529005877843,
        "return_3y": null,
        "returnsAsOf": "2026-05-18",
        "returnsSource": "FMP",
        "close": 3151.0,
        "marketCap": 834804437576,
        "pe_ttm": null,
        "valuationAsOf": "2026-05-18",
        "valuationSource": "FMP"
      }
    },
    {
      "id": "A_317",
      "type": "ASSET",
      "name": "하모닉드라이브",
      "exposure": {
        "ticker": "6324",
        "exchange": "TSE",
        "country": "JP"
      },
      "metrics": {
        "return_3d": -2.4390243902439046,
        "return_7d": 19.089316987740812,
        "return_1m": 63.65824308062575,
        "return_ytd": 77.08333333333333,
        "return_1y": 107.63358778625954,
        "return_3y": null,
        "returnsAsOf": "2026-05-18",
        "returnsSource": "FMP",
        "close": 6800.0,
        "marketCap": 643734165200,
        "pe_ttm": null,
        "valuationAsOf": "2026-05-18",
        "valuationSource": "FMP"
      }
    },
    {
      "id": "A_323",
      "type": "ASSET",
      "name": "이노반스테크놀로지",
      "exposure": {
        "ticker": "300124",
        "exchange": "SZSE",
        "country": "CN"
      },
      "metrics": {
        "return_3d": 1.1770860580695874,
        "return_7d": 2.3957643944407803,
        "return_1m": 11.93749095644625,
        "return_ytd": -1.2635609444798912,
        "return_1y": 15.256257449344446,
        "return_3y": null,
        "returnsAsOf": "2026-05-18",
        "returnsSource": "FMP",
        "close": 77.36,
        "marketCap": 209447982255,
        "pe_ttm": null,
        "valuationAsOf": "2026-05-18",
        "valuationSource": "FMP"
      }
    },
    {
      "id": "A_322",
      "type": "ASSET",
      "name": "에스턴오토메이션",
      "exposure": {
        "ticker": "002747",
        "exchange": "SZSE",
        "country": "CN"
      },
      "metrics": {
        "return_3d": 7.727272727272738,
        "return_7d": 11.125319693094626,
        "return_1m": 24.677187948350078,
        "return_ytd": 10.092905405405418,
        "return_1y": 35.99374021909232,
        "return_3y": null,
        "returnsAsOf": "2026-05-18",
        "returnsSource": "FMP",
        "close": 26.07,
        "marketCap": 22707451070,
        "pe_ttm": null,
        "valuationAsOf": "2026-05-18",
        "valuationSource": "FMP"
      }
    },
    {
      "id": "A_321",
      "type": "ASSET",
      "name": "신송로봇자동화",
      "exposure": {
        "ticker": "300024",
        "exchange": "SZSE",
        "country": "CN"
      },
      "metrics": {
        "return_3d": 5.12987012987014,
        "return_7d": 4.9935149156939085,
        "return_1m": 7.7896138482024035,
        "return_ytd": -13.003761418592141,
        "return_1y": 0.12368583797155441,
        "return_3y": null,
        "returnsAsOf": "2026-05-18",
        "returnsSource": "FMP",
        "close": 16.19,
        "marketCap": 25347386991,
        "pe_ttm": null,
        "valuationAsOf": "2026-05-18",
        "valuationSource": "FMP"
      }
    },
    {
      "id": "A_320",
      "type": "ASSET",
      "name": "에포트인텔리전트이큅먼트",
      "exposure": {
        "ticker": "688165",
        "exchange": "SSE",
        "country": "CN"
      },
      "metrics": {
        "return_3d": null,
        "return_7d": null,
        "return_1m": null,
        "return_ytd": null,
        "return_1y": null,
        "return_3y": null,
        "returnsAsOf": "2026-05-18",
        "returnsSource": "FMP",
        "close": null,
        "marketCap": null,
        "pe_ttm": null,
        "valuationAsOf": null,
        "valuationSource": null
      }
    },
    {
      "id": "M_018",
      "type": "MACRO",
      "name": "피지컬AI확산"
    },
    {
      "id": "M_023",
      "type": "MACRO",
      "name": "휴머노이드확산"
    },
    {
      "id": "C_054",
      "type": "CHARACTER",
      "name": "미국테마선도주"
    },
    {
      "id": "C_055",
      "type": "CHARACTER",
      "name": "한국테마선도주"
    },
    {
      "id": "C_056",
      "type": "CHARACTER",
      "name": "일본테마선도주"
    }
  ],
  "edges": [
    {
      "from": "A_312",
      "to": "T_038",
      "type": "THEMED_AS"
    },
    {
      "from": "A_209",
      "to": "T_038",
      "type": "THEMED_AS"
    },
    {
      "from": "A_313",
      "to": "T_038",
      "type": "THEMED_AS"
    },
    {
      "from": "A_091",
      "to": "T_038",
      "type": "THEMED_AS"
    },
    {
      "from": "A_092",
      "to": "T_038",
      "type": "THEMED_AS"
    },
    {
      "from": "A_082",
      "to": "T_038",
      "type": "THEMED_AS"
    },
    {
      "from": "A_318",
      "to": "T_038",
      "type": "THEMED_AS"
    },
    {
      "from": "A_319",
      "to": "T_038",
      "type": "THEMED_AS"
    },
    {
      "from": "A_314",
      "to": "T_038",
      "type": "THEMED_AS"
    },
    {
      "from": "A_315",
      "to": "T_038",
      "type": "THEMED_AS"
    },
    {
      "from": "A_316",
      "to": "T_038",
      "type": "THEMED_AS"
    },
    {
      "from": "A_317",
      "to": "T_038",
      "type": "THEMED_AS"
    },
    {
      "from": "A_323",
      "to": "T_038",
      "type": "THEMED_AS"
    },
    {
      "from": "A_322",
      "to": "T_038",
      "type": "THEMED_AS"
    },
    {
      "from": "A_321",
      "to": "T_038",
      "type": "THEMED_AS"
    },
    {
      "from": "A_320",
      "to": "T_038",
      "type": "THEMED_AS"
    },
    {
      "from": "M_018",
      "to": "T_038",
      "type": "IMPACTS"
    },
    {
      "from": "M_023",
      "to": "T_038",
      "type": "IMPACTS"
    },
    {
      "from": "A_312",
      "to": "C_054",
      "type": "HAS_TRAIT"
    },
    {
      "from": "A_091",
      "to": "C_055",
      "type": "HAS_TRAIT"
    },
    {
      "from": "A_314",
      "to": "C_056",
      "type": "HAS_TRAIT"
    }
  ],
  "links": [
    {
      "from": "A_312",
      "to": "T_038",
      "type": "THEMED_AS"
    },
    {
      "from": "A_209",
      "to": "T_038",
      "type": "THEMED_AS"
    },
    {
      "from": "A_313",
      "to": "T_038",
      "type": "THEMED_AS"
    },
    {
      "from": "A_091",
      "to": "T_038",
      "type": "THEMED_AS"
    },
    {
      "from": "A_092",
      "to": "T_038",
      "type": "THEMED_AS"
    },
    {
      "from": "A_082",
      "to": "T_038",
      "type": "THEMED_AS"
    },
    {
      "from": "A_318",
      "to": "T_038",
      "type": "THEMED_AS"
    },
    {
      "from": "A_319",
      "to": "T_038",
      "type": "THEMED_AS"
    },
    {
      "from": "A_314",
      "to": "T_038",
      "type": "THEMED_AS"
    },
    {
      "from": "A_315",
      "to": "T_038",
      "type": "THEMED_AS"
    },
    {
      "from": "A_316",
      "to": "T_038",
      "type": "THEMED_AS"
    },
    {
      "from": "A_317",
      "to": "T_038",
      "type": "THEMED_AS"
    },
    {
      "from": "A_323",
      "to": "T_038",
      "type": "THEMED_AS"
    },
    {
      "from": "A_322",
      "to": "T_038",
      "type": "THEMED_AS"
    },
    {
      "from": "A_321",
      "to": "T_038",
      "type": "THEMED_AS"
    },
    {
      "from": "A_320",
      "to": "T_038",
      "type": "THEMED_AS"
    },
    {
      "from": "M_018",
      "to": "T_038",
      "type": "IMPACTS"
    },
    {
      "from": "M_023",
      "to": "T_038",
      "type": "IMPACTS"
    },
    {
      "from": "A_312",
      "to": "C_054",
      "type": "HAS_TRAIT"
    },
    {
      "from": "A_091",
      "to": "C_055",
      "type": "HAS_TRAIT"
    },
    {
      "from": "A_314",
      "to": "C_056",
      "type": "HAS_TRAIT"
    }
  ]
}