{
  "schemaVersion": "v5",
  "themeId": "T_068",
  "themeName": "K방산소부장",
  "meta": {
    "periodDefault": "3d",
    "periodOptions": [
      "3d",
      "7d",
      "1m",
      "ytd",
      "1y",
      "3y"
    ],
    "dataAsOf": "2026-03-25T00:00:00+09:00",
    "notes": "g68 누적 import 기반 K방산 소부장 테마",
    "sources": []
  },
  "nodes": [
    {
      "id": "T_068",
      "type": "THEME",
      "name": "K방산소부장"
    },
    {
      "id": "A_570",
      "type": "ASSET",
      "name": "코츠테크놀로지",
      "exposure": {
        "ticker": "448710",
        "exchange": "KOSDAQ",
        "country": "KR"
      },
      "metrics": {
        "close": null,
        "marketCap": null,
        "pe_ttm": null,
        "valuationAsOf": null,
        "valuationSource": null,
        "return_3d": 0.37878787878788955,
        "return_7d": -8.39506172839506,
        "return_1m": -2.4710830704521514,
        "return_ytd": 5.099150141643061,
        "return_1y": -1.591511936339518,
        "return_3y": null,
        "returnsAsOf": "2026-03-27",
        "returnsSource": "PYKRX"
      }
    },
    {
      "id": "A_571",
      "type": "ASSET",
      "name": "퍼스텍",
      "exposure": {
        "ticker": "010820",
        "exchange": "KOSPI",
        "country": "KR"
      },
      "metrics": {
        "close": null,
        "marketCap": null,
        "pe_ttm": null,
        "valuationAsOf": null,
        "valuationSource": null,
        "return_3d": 3.32850940665701,
        "return_7d": -5.430463576158939,
        "return_1m": -1.3812154696132617,
        "return_ytd": 78.49999999999999,
        "return_1y": 91.93548387096774,
        "return_3y": 114.73684210526316,
        "returnsAsOf": "2026-03-27",
        "returnsSource": "PYKRX"
      }
    },
    {
      "id": "A_572",
      "type": "ASSET",
      "name": "엠앤씨솔루션",
      "exposure": {
        "ticker": "484870",
        "exchange": "KOSPI",
        "country": "KR"
      },
      "metrics": {
        "close": null,
        "marketCap": null,
        "pe_ttm": null,
        "valuationAsOf": null,
        "valuationSource": null,
        "return_3d": -5.321100917431187,
        "return_7d": -16.57235246564268,
        "return_1m": -26.80851063829788,
        "return_ytd": -26.80851063829788,
        "return_1y": 30.63291139240507,
        "return_3y": null,
        "returnsAsOf": "2026-03-27",
        "returnsSource": "PYKRX"
      }
    },
    {
      "id": "A_573",
      "type": "ASSET",
      "name": "SNT다이내믹스",
      "exposure": {
        "ticker": "003570",
        "exchange": "KOSPI",
        "country": "KR"
      },
      "metrics": {
        "close": null,
        "marketCap": null,
        "pe_ttm": null,
        "valuationAsOf": null,
        "valuationSource": null,
        "return_3d": 4.8523206751054815,
        "return_7d": 1.4285714285714235,
        "return_1m": -14.897260273972602,
        "return_ytd": 10.690423162583528,
        "return_1y": 41.79743223965764,
        "return_3y": 414.4927536231884,
        "returnsAsOf": "2026-03-27",
        "returnsSource": "PYKRX"
      }
    },
    {
      "id": "A_574",
      "type": "ASSET",
      "name": "STX엔진",
      "exposure": {
        "ticker": "077970",
        "exchange": "KOSPI",
        "country": "KR"
      },
      "metrics": {
        "close": null,
        "marketCap": null,
        "pe_ttm": null,
        "valuationAsOf": null,
        "valuationSource": null,
        "return_3d": -1.179941002949858,
        "return_7d": -3.597122302158273,
        "return_1m": -3.458213256484155,
        "return_ytd": 0.1494768310911887,
        "return_1y": 31.115459882583174,
        "return_3y": 143.28249818445897,
        "returnsAsOf": "2026-03-27",
        "returnsSource": "PYKRX"
      }
    },
    {
      "id": "A_575",
      "type": "ASSET",
      "name": "삼양컴텍",
      "exposure": {
        "ticker": "484590",
        "exchange": "KOSDAQ",
        "country": "KR"
      },
      "metrics": {
        "close": null,
        "marketCap": null,
        "pe_ttm": null,
        "valuationAsOf": null,
        "valuationSource": null,
        "return_3d": 1.187446988973706,
        "return_7d": -5.988967691095349,
        "return_1m": -3.5569927243330635,
        "return_ytd": -10.970149253731343,
        "return_1y": null,
        "return_3y": null,
        "returnsAsOf": "2026-03-27",
        "returnsSource": "PYKRX"
      }
    },
    {
      "id": "A_576",
      "type": "ASSET",
      "name": "풍산",
      "exposure": {
        "ticker": "103140",
        "exchange": "KOSPI",
        "country": "KR"
      },
      "metrics": {
        "close": null,
        "marketCap": null,
        "pe_ttm": null,
        "valuationAsOf": null,
        "valuationSource": null,
        "return_3d": -1.9251336898395754,
        "return_7d": -10.44921875,
        "return_1m": -21.016365202411713,
        "return_ytd": -14.058106841611995,
        "return_1y": 41.73106646058733,
        "return_3y": 166.56976744186048,
        "returnsAsOf": "2026-03-27",
        "returnsSource": "PYKRX"
      }
    },
    {
      "id": "A_577",
      "type": "ASSET",
      "name": "켄코아에어로스페이스",
      "exposure": {
        "ticker": "274090",
        "exchange": "KOSDAQ",
        "country": "KR"
      },
      "metrics": {
        "close": null,
        "marketCap": null,
        "pe_ttm": null,
        "valuationAsOf": null,
        "valuationSource": null,
        "return_3d": 13.285024154589365,
        "return_7d": 8.314087759815237,
        "return_1m": 1.2958963282937441,
        "return_ytd": 25.33404596472475,
        "return_1y": 69.4364161849711,
        "return_3y": 52.17391304347827,
        "returnsAsOf": "2026-03-27",
        "returnsSource": "PYKRX"
      }
    },
    {
      "id": "A_578",
      "type": "ASSET",
      "name": "비츠로테크",
      "exposure": {
        "ticker": "042370",
        "exchange": "KOSDAQ",
        "country": "KR"
      },
      "metrics": {
        "close": null,
        "marketCap": null,
        "pe_ttm": null,
        "valuationAsOf": null,
        "valuationSource": null,
        "return_3d": -1.379310344827589,
        "return_7d": 1.0600706713780994,
        "return_1m": 3.342366757000903,
        "return_ytd": 25.43859649122806,
        "return_1y": 42.643391521197,
        "return_3y": 58.2295988934993,
        "returnsAsOf": "2026-03-27",
        "returnsSource": "PYKRX"
      }
    },
    {
      "id": "A_579",
      "type": "ASSET",
      "name": "RFHIC",
      "exposure": {
        "ticker": "218410",
        "exchange": "KOSDAQ",
        "country": "KR"
      },
      "metrics": {
        "close": null,
        "marketCap": null,
        "pe_ttm": null,
        "valuationAsOf": null,
        "valuationSource": null,
        "return_3d": 7.853403141361248,
        "return_7d": 5.23627075351214,
        "return_1m": 45.07042253521127,
        "return_ytd": 135.09272467902997,
        "return_1y": 420.85967130214914,
        "return_3y": 237.01431492842536,
        "returnsAsOf": "2026-03-27",
        "returnsSource": "PYKRX"
      }
    },
    {
      "id": "A_580",
      "type": "ASSET",
      "name": "아이쓰리시스템",
      "exposure": {
        "ticker": "214430",
        "exchange": "KOSDAQ",
        "country": "KR"
      },
      "metrics": {
        "close": null,
        "marketCap": null,
        "pe_ttm": null,
        "valuationAsOf": null,
        "valuationSource": null,
        "return_3d": -0.7446808510638281,
        "return_7d": -8.259587020648972,
        "return_1m": -12.064090480678601,
        "return_ytd": 16.91729323308271,
        "return_1y": 63.68421052631579,
        "return_3y": 331.94444444444446,
        "returnsAsOf": "2026-03-27",
        "returnsSource": "PYKRX"
      }
    },
    {
      "id": "BF_128",
      "type": "BUSINESS_FIELD",
      "name": "지상화력/기동"
    },
    {
      "id": "BF_129",
      "type": "BUSINESS_FIELD",
      "name": "유도무기·레이더·전자전"
    },
    {
      "id": "BF_130",
      "type": "BUSINESS_FIELD",
      "name": "항공/우주"
    }
  ],
  "edges": [
    {
      "from": "A_570",
      "to": "T_068",
      "type": "THEMED_AS"
    },
    {
      "from": "A_571",
      "to": "T_068",
      "type": "THEMED_AS"
    },
    {
      "from": "A_572",
      "to": "T_068",
      "type": "THEMED_AS"
    },
    {
      "from": "A_573",
      "to": "T_068",
      "type": "THEMED_AS"
    },
    {
      "from": "A_574",
      "to": "T_068",
      "type": "THEMED_AS"
    },
    {
      "from": "A_575",
      "to": "T_068",
      "type": "THEMED_AS"
    },
    {
      "from": "A_576",
      "to": "T_068",
      "type": "THEMED_AS"
    },
    {
      "from": "A_577",
      "to": "T_068",
      "type": "THEMED_AS"
    },
    {
      "from": "A_578",
      "to": "T_068",
      "type": "THEMED_AS"
    },
    {
      "from": "A_579",
      "to": "T_068",
      "type": "THEMED_AS"
    },
    {
      "from": "A_580",
      "to": "T_068",
      "type": "THEMED_AS"
    },
    {
      "from": "A_570",
      "to": "BF_128",
      "type": "OPERATES"
    },
    {
      "from": "A_571",
      "to": "BF_128",
      "type": "OPERATES"
    },
    {
      "from": "A_572",
      "to": "BF_128",
      "type": "OPERATES"
    },
    {
      "from": "A_573",
      "to": "BF_128",
      "type": "OPERATES"
    },
    {
      "from": "A_574",
      "to": "BF_128",
      "type": "OPERATES"
    },
    {
      "from": "A_575",
      "to": "BF_128",
      "type": "OPERATES"
    },
    {
      "from": "A_576",
      "to": "BF_128",
      "type": "OPERATES"
    },
    {
      "from": "A_580",
      "to": "BF_129",
      "type": "OPERATES"
    },
    {
      "from": "A_579",
      "to": "BF_129",
      "type": "OPERATES"
    },
    {
      "from": "A_578",
      "to": "BF_129",
      "type": "OPERATES"
    },
    {
      "from": "A_577",
      "to": "BF_130",
      "type": "OPERATES"
    },
    {
      "from": "A_578",
      "to": "BF_130",
      "type": "OPERATES"
    }
  ],
  "links": [
    {
      "from": "A_570",
      "to": "T_068",
      "type": "THEMED_AS"
    },
    {
      "from": "A_571",
      "to": "T_068",
      "type": "THEMED_AS"
    },
    {
      "from": "A_572",
      "to": "T_068",
      "type": "THEMED_AS"
    },
    {
      "from": "A_573",
      "to": "T_068",
      "type": "THEMED_AS"
    },
    {
      "from": "A_574",
      "to": "T_068",
      "type": "THEMED_AS"
    },
    {
      "from": "A_575",
      "to": "T_068",
      "type": "THEMED_AS"
    },
    {
      "from": "A_576",
      "to": "T_068",
      "type": "THEMED_AS"
    },
    {
      "from": "A_577",
      "to": "T_068",
      "type": "THEMED_AS"
    },
    {
      "from": "A_578",
      "to": "T_068",
      "type": "THEMED_AS"
    },
    {
      "from": "A_579",
      "to": "T_068",
      "type": "THEMED_AS"
    },
    {
      "from": "A_580",
      "to": "T_068",
      "type": "THEMED_AS"
    },
    {
      "from": "A_570",
      "to": "BF_128",
      "type": "OPERATES"
    },
    {
      "from": "A_571",
      "to": "BF_128",
      "type": "OPERATES"
    },
    {
      "from": "A_572",
      "to": "BF_128",
      "type": "OPERATES"
    },
    {
      "from": "A_573",
      "to": "BF_128",
      "type": "OPERATES"
    },
    {
      "from": "A_574",
      "to": "BF_128",
      "type": "OPERATES"
    },
    {
      "from": "A_575",
      "to": "BF_128",
      "type": "OPERATES"
    },
    {
      "from": "A_576",
      "to": "BF_128",
      "type": "OPERATES"
    },
    {
      "from": "A_580",
      "to": "BF_129",
      "type": "OPERATES"
    },
    {
      "from": "A_579",
      "to": "BF_129",
      "type": "OPERATES"
    },
    {
      "from": "A_578",
      "to": "BF_129",
      "type": "OPERATES"
    },
    {
      "from": "A_577",
      "to": "BF_130",
      "type": "OPERATES"
    },
    {
      "from": "A_578",
      "to": "BF_130",
      "type": "OPERATES"
    }
  ]
}