{
  "schemaVersion": "v5",
  "themeId": "T_525",
  "themeName": "(Y20) 코로나 팬데믹·언택트",
  "meta": {
    "periodDefault": "3d",
    "periodOptions": [
      "1d",
      "3d",
      "7d",
      "15d",
      "1m",
      "ytd",
      "1y",
      "2y",
      "3y"
    ],
    "dataAsOf": "2026-06-24T00:00:00+09:00",
    "description": "코로나 팬데믹·언택트 — 2020 회고 테마.",
    "notes": "T_525 신규 회고((Y20)). 자산별 CHARACTER, MACRO 3(재사용)",
    "sources": []
  },
  "nodes": [
    {
      "id": "T_525",
      "type": "THEME",
      "name": "(Y20) 코로나 팬데믹·언택트"
    },
    {
      "id": "A_213",
      "type": "ASSET",
      "name": "줌비디오",
      "exposure": {
        "ticker": "ZM",
        "exchange": "NASDAQ",
        "country": "US"
      },
      "metrics": {
        "return_1d": -2.5129087779690362,
        "return_3d": -1.564129301355588,
        "return_7d": -0.5967005967006056,
        "return_15d": -7.9722703639514725,
        "return_1m": -20.000000000000007,
        "return_ytd": 1.9683149303888703,
        "return_1y": 9.498646732826387,
        "return_2y": 43.53775975671566,
        "return_3y": 23.686126073664294,
        "close": 84.96,
        "marketCap": 24913009496,
        "pe_ttm": null,
        "valuationAsOf": "2026-07-06",
        "valuationSource": "FMP",
        "returnsAsOf": "2026-07-06",
        "returnsSource": "FMP"
      }
    },
    {
      "id": "C_1336",
      "type": "CHARACTER",
      "name": "화상회의 — 언택트 상징"
    },
    {
      "id": "A_326",
      "type": "ASSET",
      "name": "넷플릭스",
      "exposure": {
        "ticker": "NFLX",
        "exchange": "NASDAQ",
        "country": "US"
      },
      "metrics": {
        "return_1d": -2.099162910495822,
        "return_3d": 6.470588235294095,
        "return_7d": 5.818485523385286,
        "return_15d": -6.459948320413433,
        "return_1m": -6.746810598626107,
        "return_ytd": -16.4523574019123,
        "return_1y": -40.835862713051604,
        "return_2y": 12.638909468069336,
        "return_3y": 76.87296416938112,
        "close": 76.02,
        "marketCap": 320105016000,
        "pe_ttm": null,
        "valuationAsOf": "2026-07-06",
        "valuationSource": "FMP",
        "returnsAsOf": "2026-07-06",
        "returnsSource": "FMP"
      }
    },
    {
      "id": "C_1337",
      "type": "CHARACTER",
      "name": "스트리밍 — 집콕 수혜"
    },
    {
      "id": "A_211",
      "type": "ASSET",
      "name": "아마존",
      "exposure": {
        "ticker": "AMZN",
        "exchange": "NASDAQ",
        "country": "US"
      },
      "metrics": {
        "return_1d": 0.6140025549099537,
        "return_3d": 2.4418897373500004,
        "return_7d": 4.2216246211636,
        "return_15d": 1.097263053289721,
        "return_1m": -2.343812495000408,
        "return_ytd": 7.796909492273718,
        "return_1y": 11.022189887231715,
        "return_2y": 26.344113842173343,
        "return_3y": 89.21264724116553,
        "close": 244.16,
        "marketCap": 2626453536000,
        "pe_ttm": null,
        "valuationAsOf": "2026-07-06",
        "valuationSource": "FMP",
        "returnsAsOf": "2026-07-06",
        "returnsSource": "FMP"
      }
    },
    {
      "id": "C_1338",
      "type": "CHARACTER",
      "name": "이커머스·클라우드 폭발"
    },
    {
      "id": "A_513",
      "type": "ASSET",
      "name": "NAVER",
      "exposure": {
        "ticker": "035420",
        "exchange": "KOSPI",
        "country": "KR"
      },
      "metrics": {
        "return_1d": null,
        "return_3d": -0.4052684903748771,
        "return_7d": -1.552328492739108,
        "return_15d": null,
        "return_1m": -23.05283757338552,
        "return_ytd": -19.56875482836773,
        "return_1y": -31.612676242190407,
        "return_2y": null,
        "return_3y": null,
        "close": 196600,
        "marketCap": null,
        "pe_ttm": null,
        "valuationAsOf": "2026-07-06",
        "valuationSource": "EODHD",
        "returnsAsOf": "2026-07-06",
        "returnsSource": "EODHD"
      }
    },
    {
      "id": "C_1339",
      "type": "CHARACTER",
      "name": "커머스·콘텐츠 언택트"
    },
    {
      "id": "A_2548",
      "type": "ASSET",
      "name": "펠로톤",
      "exposure": {
        "ticker": "PTON",
        "exchange": "NASDAQ",
        "country": "US"
      },
      "metrics": {
        "return_1d": 2.086956521739136,
        "return_3d": -0.6768189509306244,
        "return_7d": 2.44328097731239,
        "return_15d": 3.8938053097345104,
        "return_1m": -2.166666666666661,
        "return_ytd": -4.084967320261434,
        "return_1y": -11.195158850226928,
        "return_2y": 73.66863905325445,
        "return_3y": -19.5890410958904,
        "close": 5.87,
        "marketCap": 2448699850,
        "pe_ttm": null,
        "valuationAsOf": "2026-07-06",
        "valuationSource": "FMP",
        "returnsAsOf": "2026-07-06",
        "returnsSource": "FMP"
      }
    },
    {
      "id": "C_1340",
      "type": "CHARACTER",
      "name": "홈피트니스 — 집콕"
    },
    {
      "id": "A_2549",
      "type": "ASSET",
      "name": "도큐사인",
      "exposure": {
        "ticker": "DOCU",
        "exchange": "NASDAQ",
        "country": "US"
      },
      "metrics": {
        "return_1d": 2.468866069477804,
        "return_3d": 5.583070688878866,
        "return_7d": 6.012658227848089,
        "return_15d": 5.274971941638618,
        "return_1m": -10.496183206106869,
        "return_ytd": -27.679259830377788,
        "return_1y": -39.209332469215816,
        "return_2y": -12.336448598130845,
        "return_3y": -9.31941221964424,
        "close": 46.9,
        "marketCap": 8955320500,
        "pe_ttm": null,
        "valuationAsOf": "2026-07-06",
        "valuationSource": "FMP",
        "returnsAsOf": "2026-07-06",
        "returnsSource": "FMP"
      }
    },
    {
      "id": "C_1341",
      "type": "CHARACTER",
      "name": "전자서명 — 언택트"
    },
    {
      "id": "A_1632",
      "type": "ASSET",
      "name": "모더나",
      "exposure": {
        "ticker": "MRNA",
        "exchange": "NASDAQ",
        "country": "US"
      },
      "metrics": {
        "return_1d": 2.5576730190571606,
        "return_3d": 16.807082678851913,
        "return_7d": 35.38563389606091,
        "return_15d": 64.78646253021756,
        "return_1m": 66.734610680799,
        "return_ytd": 165.06804925469862,
        "return_1y": 170.14531043593132,
        "return_2y": -31.11578947368421,
        "return_3y": -33.4959349593496,
        "close": 81.8,
        "marketCap": 32457094800,
        "pe_ttm": null,
        "valuationAsOf": "2026-07-06",
        "valuationSource": "FMP",
        "returnsAsOf": "2026-07-06",
        "returnsSource": "FMP"
      }
    },
    {
      "id": "C_1342",
      "type": "CHARACTER",
      "name": "mRNA 백신"
    },
    {
      "id": "M_146",
      "type": "MACRO",
      "name": "이커머스확대"
    },
    {
      "id": "M_244",
      "type": "MACRO",
      "name": "클라우드"
    },
    {
      "id": "M_069",
      "type": "MACRO",
      "name": "유동성확대"
    }
  ],
  "edges": [
    {
      "from": "A_213",
      "to": "T_525",
      "type": "THEMED_AS"
    },
    {
      "from": "A_213",
      "to": "C_1336",
      "type": "HAS_TRAIT"
    },
    {
      "from": "A_326",
      "to": "T_525",
      "type": "THEMED_AS"
    },
    {
      "from": "A_326",
      "to": "C_1337",
      "type": "HAS_TRAIT"
    },
    {
      "from": "A_211",
      "to": "T_525",
      "type": "THEMED_AS"
    },
    {
      "from": "A_211",
      "to": "C_1338",
      "type": "HAS_TRAIT"
    },
    {
      "from": "A_513",
      "to": "T_525",
      "type": "THEMED_AS"
    },
    {
      "from": "A_513",
      "to": "C_1339",
      "type": "HAS_TRAIT"
    },
    {
      "from": "A_2548",
      "to": "T_525",
      "type": "THEMED_AS"
    },
    {
      "from": "A_2548",
      "to": "C_1340",
      "type": "HAS_TRAIT"
    },
    {
      "from": "A_2549",
      "to": "T_525",
      "type": "THEMED_AS"
    },
    {
      "from": "A_2549",
      "to": "C_1341",
      "type": "HAS_TRAIT"
    },
    {
      "from": "A_1632",
      "to": "T_525",
      "type": "THEMED_AS"
    },
    {
      "from": "A_1632",
      "to": "C_1342",
      "type": "HAS_TRAIT"
    },
    {
      "from": "M_146",
      "to": "T_525",
      "type": "IMPACTS"
    },
    {
      "from": "M_244",
      "to": "T_525",
      "type": "IMPACTS"
    },
    {
      "from": "M_069",
      "to": "T_525",
      "type": "IMPACTS"
    }
  ],
  "links": [
    {
      "from": "A_213",
      "to": "T_525",
      "type": "THEMED_AS"
    },
    {
      "from": "A_213",
      "to": "C_1336",
      "type": "HAS_TRAIT"
    },
    {
      "from": "A_326",
      "to": "T_525",
      "type": "THEMED_AS"
    },
    {
      "from": "A_326",
      "to": "C_1337",
      "type": "HAS_TRAIT"
    },
    {
      "from": "A_211",
      "to": "T_525",
      "type": "THEMED_AS"
    },
    {
      "from": "A_211",
      "to": "C_1338",
      "type": "HAS_TRAIT"
    },
    {
      "from": "A_513",
      "to": "T_525",
      "type": "THEMED_AS"
    },
    {
      "from": "A_513",
      "to": "C_1339",
      "type": "HAS_TRAIT"
    },
    {
      "from": "A_2548",
      "to": "T_525",
      "type": "THEMED_AS"
    },
    {
      "from": "A_2548",
      "to": "C_1340",
      "type": "HAS_TRAIT"
    },
    {
      "from": "A_2549",
      "to": "T_525",
      "type": "THEMED_AS"
    },
    {
      "from": "A_2549",
      "to": "C_1341",
      "type": "HAS_TRAIT"
    },
    {
      "from": "A_1632",
      "to": "T_525",
      "type": "THEMED_AS"
    },
    {
      "from": "A_1632",
      "to": "C_1342",
      "type": "HAS_TRAIT"
    },
    {
      "from": "M_146",
      "to": "T_525",
      "type": "IMPACTS"
    },
    {
      "from": "M_244",
      "to": "T_525",
      "type": "IMPACTS"
    },
    {
      "from": "M_069",
      "to": "T_525",
      "type": "IMPACTS"
    }
  ]
}